PLANit_Python-0.4.0.data/data/share/planit/planit-all-0.4.0.jar
planit/Planit.py
planit/__init__.py
planit/converter.py
planit/converterwrappers.py
planit/enums.py
planit/gateway.py
planit/initial_cost.py
planit/project.py
planit/projectwrappers.py
planit/version.py
planit/wrappers.py
test_utils/__init__.py
test_utils/test_utils.py
PLANit_Python-0.4.0.dist-info/LICENSE.txt
PLANit_Python-0.4.0.dist-info/METADATA
PLANit_Python-0.4.0.dist-info/WHEEL
PLANit_Python-0.4.0.dist-info/top_level.txt
PLANit_Python-0.4.0.dist-info/RECORD
